setup.py
Flask_SocialAPI.egg-info/PKG-INFO
Flask_SocialAPI.egg-info/SOURCES.txt
Flask_SocialAPI.egg-info/dependency_links.txt
Flask_SocialAPI.egg-info/not-zip-safe
Flask_SocialAPI.egg-info/requires.txt
Flask_SocialAPI.egg-info/top_level.txt
flask_socialapi/__init__.py
flask_socialapi/core.py
flask_socialapi/providers/facebook.py
flask_socialapi/providers/google.py
flask_socialapi/providers/naver.py