Metadata-Version: 1.0
Name: Flask-SocialAPI
Version: 1.0.3
Summary: Simple api for controlling and login to provider
Home-page: https://github.com/leejaedus/Flask-SocialAPI
Author: Lee Jae Yeon
Author-email: leejaeduss@gmail.com
License: UNKNOWN
Platform: UNKNOWN
